Metadata-Version: 2.1
Name: dlgpu-assistant
Version: 1.6
Summary: Use this tools to improve your ANN
Home-page: UNKNOWN
Author: Rubén Hinojar
License: MIT
Platform: UNKNOWN
License-File: LICENSE.txt
